{
  "data": {
    "article": {},
    "attachments": {
      "media_keys": [
        "3_1831642559719878656"
      ]
    },
    "author_id": "1643490407094030338",
    "conversation_id": "1831642580918136929",
    "created_at": "2024-09-05T10:36:36.000Z",
    "edit_controls": {
      "editable_until": "2024-09-05T11:36:36.000Z",
      "edits_remaining": 5,
      "is_edit_eligible": true
    },
    "edit_history_tweet_ids": [
      "1831642580918136929"
    ],
    "entities": {
      "urls": [
        {
          "display_url": "pic.x.com/eqhyf45hvp",
          "end": 38,
          "expanded_url": "https://twitter.com/Usam8964/status/1831642580918136929/photo/1",
          "media_key": "3_1831642559719878656",
          "start": 15,
          "url": "https://t.co/EQHYF45hVP"
        }
      ]
    },
    "geo": {},
    "id": "1831642580918136929",
    "lang": "zh",
    "possibly_sensitive": false,
    "public_metrics": {
      "bookmark_count": 0,
      "impression_count": 0,
      "like_count": 0,
      "quote_count": 0,
      "reply_count": 0,
      "retweet_count": 0
    },
    "reply_settings": "everyone",
    "text": "70个币，35抓\n收获如下： https://t.co/EQHYF45hVP"
  },
  "includes": {
    "media": [
      {
        "height": 2048,
        "media_key": "3_1831642559719878656",
        "public_metrics": {},
        "type": "photo",
        "url": "https://pbs.twimg.com/media/GWtNNB-XMAA0JgX.jpg",
        "width": 1536
      }
    ],
    "tweets": [
      {
        "article": {},
        "attachments": {
          "media_keys": [
            "3_1831642559719878656"
          ]
        },
        "author_id": "1643490407094030338",
        "conversation_id": "1831642580918136929",
        "created_at": "2024-09-05T10:36:36.000Z",
        "edit_controls": {
          "editable_until": "2024-09-05T11:36:36.000Z",
          "edits_remaining": 5,
          "is_edit_eligible": true
        },
        "edit_history_tweet_ids": [
          "1831642580918136929"
        ],
        "entities": {
          "urls": [
            {
              "display_url": "pic.x.com/eqhyf45hvp",
              "end": 38,
              "expanded_url": "https://twitter.com/Usam8964/status/1831642580918136929/photo/1",
              "media_key": "3_1831642559719878656",
              "start": 15,
              "url": "https://t.co/EQHYF45hVP"
            }
          ]
        },
        "geo": {},
        "id": "1831642580918136929",
        "lang": "zh",
        "possibly_sensitive": false,
        "public_metrics": {
          "bookmark_count": 0,
          "impression_count": 0,
          "like_count": 0,
          "quote_count": 0,
          "reply_count": 0,
          "retweet_count": 0
        },
        "reply_settings": "everyone",
        "text": "70个币，35抓\n收获如下： https://t.co/EQHYF45hVP"
      }
    ],
    "users": [
      {
        "created_at": "2023-04-05T05:47:19.000Z",
        "description": "MTF/家长党/社交废物/含糖/在读JK/物理苦手/INFP-T/纯生活推\nNow 正體中文/简体中文/日本語/English supported.\nvx🚪50同类免费，时不时发朋友圈，陪聊可接",
        "id": "1643490407094030338",
        "name": "イレンナ🍥伊莲娜",
        "profile_image_url": "https://pbs.twimg.com/profile_images/1643490479798112256/rWNEsRLN_normal.png",
        "protected": false,
        "public_metrics": {
          "followers_count": 1544,
          "following_count": 829,
          "like_count": 22639,
          "listed_count": 2,
          "tweet_count": 2805
        },
        "username": "Usam8964",
        "verified": false
      }
    ]
  }
}