{
  "data": {
    "article": {},
    "attachments": {},
    "author_id": "1643490407094030338",
    "conversation_id": "1842564202579595729",
    "created_at": "2024-10-06T02:34:00.000Z",
    "edit_controls": {
      "editable_until": "2024-10-06T03:34:00.000Z",
      "edits_remaining": 5,
      "is_edit_eligible": false
    },
    "edit_history_tweet_ids": [
      "1842755154438926528"
    ],
    "entities": {
      "mentions": [
        {
          "end": 11,
          "id": "1691334965458604032",
          "start": 0,
          "username": "Siyan_Xiao"
        },
        {
          "end": 26,
          "id": "1688233455363219456",
          "start": 12,
          "username": "Susiethegamer"
        }
      ]
    },
    "geo": {},
    "id": "1842755154438926528",
    "in_reply_to_user_id": "1691334965458604032",
    "lang": "zh",
    "possibly_sensitive": false,
    "public_metrics": {
      "bookmark_count": 0,
      "impression_count": 0,
      "like_count": 0,
      "quote_count": 0,
      "reply_count": 0,
      "retweet_count": 0
    },
    "referenced_tweets": [
      {
        "id": "1842669926345232679",
        "type": "replied_to"
      }
    ],
    "reply_settings": "everyone",
    "text": "@Siyan_Xiao @Susiethegamer 绝对是美女姐姐🥺"
  },
  "includes": {
    "tweets": [
      {
        "article": {},
        "attachments": {},
        "author_id": "1643490407094030338",
        "conversation_id": "1842564202579595729",
        "created_at": "2024-10-06T02:34:00.000Z",
        "edit_controls": {
          "editable_until": "2024-10-06T03:34:00.000Z",
          "edits_remaining": 5,
          "is_edit_eligible": false
        },
        "edit_history_tweet_ids": [
          "1842755154438926528"
        ],
        "entities": {
          "mentions": [
            {
              "end": 11,
              "id": "1691334965458604032",
              "start": 0,
              "username": "Siyan_Xiao"
            },
            {
              "end": 26,
              "id": "1688233455363219456",
              "start": 12,
              "username": "Susiethegamer"
            }
          ]
        },
        "geo": {},
        "id": "1842755154438926528",
        "in_reply_to_user_id": "1691334965458604032",
        "lang": "zh",
        "possibly_sensitive": false,
        "public_metrics": {
          "bookmark_count": 0,
          "impression_count": 0,
          "like_count": 0,
          "quote_count": 0,
          "reply_count": 0,
          "retweet_count": 0
        },
        "referenced_tweets": [
          {
            "id": "1842669926345232679",
            "type": "replied_to"
          }
        ],
        "reply_settings": "everyone",
        "text": "@Siyan_Xiao @Susiethegamer 绝对是美女姐姐🥺"
      },
      {
        "article": {},
        "attachments": {
          "media_keys": [
            "3_1842669921899008000"
          ]
        },
        "author_id": "1691334965458604032",
        "conversation_id": "1842564202579595729",
        "created_at": "2024-10-05T20:55:20.000Z",
        "edit_controls": {
          "editable_until": "2024-10-05T21:55:20.000Z",
          "edits_remaining": 5,
          "is_edit_eligible": false
        },
        "edit_history_tweet_ids": [
          "1842669926345232679"
        ],
        "entities": {
          "mentions": [
            {
              "end": 14,
              "id": "1688233455363219456",
              "start": 0,
              "username": "Susiethegamer"
            }
          ],
          "urls": [
            {
              "display_url": "pic.x.com/f4QqkNZzPr",
              "end": 49,
              "expanded_url": "https://x.com/Siyan_Xiao/status/1842669926345232679/photo/1",
              "media_key": "3_1842669921899008000",
              "start": 26,
              "url": "https://t.co/f4QqkNZzPr"
            }
          ]
        },
        "geo": {},
        "id": "1842669926345232679",
        "in_reply_to_user_id": "1688233455363219456",
        "lang": "zh",
        "possibly_sensitive": false,
        "public_metrics": {
          "bookmark_count": 0,
          "impression_count": 172,
          "like_count": 15,
          "quote_count": 0,
          "reply_count": 5,
          "retweet_count": 0
        },
        "referenced_tweets": [
          {
            "id": "1842564202579595729",
            "type": "replied_to"
          }
        ],
        "reply_settings": "everyone",
        "text": "@Susiethegamer 我无美颜，一眼长发男 https://t.co/f4QqkNZzPr"
      }
    ],
    "users": [
      {
        "created_at": "2023-04-05T05:47:19.000Z",
        "description": "MTF/家长党/社交废物/含糖/在读JK/物理苦手/INFP-T/纯生活推\nNow 正體中文/简体中文/日本語/English supported.\nvx🚪50同类免费，时不时发朋友圈，陪聊可接",
        "id": "1643490407094030338",
        "name": "イレンナ🍥伊莲娜",
        "profile_image_url": "https://pbs.twimg.com/profile_images/1643490479798112256/rWNEsRLN_normal.png",
        "protected": false,
        "public_metrics": {
          "followers_count": 1825,
          "following_count": 903,
          "like_count": 25499,
          "listed_count": 4,
          "tweet_count": 3095
        },
        "username": "Usam8964",
        "verified": false
      },
      {
        "created_at": "2023-08-15T06:24:34.000Z",
        "description": "ENTJ/跨性别女生🏳️‍⚧️/UG in @EdinburghUni 🏴󠁧󠁢󠁳󠁣󠁴󠁿🇬🇧//Citywalk 爱好者/《冰与火之歌》及其相关系列的爱好者/UMA和灵异事件爱好者/是只可爱的海豹宝宝，咱的豹妈妈：@amegumi666/分享些日常",
        "entities": {
          "description": {
            "mentions": [
              {
                "end": 35,
                "start": 22,
                "username": "EdinburghUni"
              },
              {
                "end": 118,
                "start": 107,
                "username": "amegumi666"
              }
            ]
          }
        },
        "id": "1691334965458604032",
        "location": "Edinburgh, United Kingdom",
        "name": "思言",
        "pinned_tweet_id": "1840130684549013532",
        "profile_image_url": "https://pbs.twimg.com/profile_images/1795740402592743424/aS5D5tGy_normal.jpg",
        "protected": false,
        "public_metrics": {
          "followers_count": 1223,
          "following_count": 1293,
          "like_count": 24193,
          "listed_count": 3,
          "tweet_count": 7356
        },
        "username": "Siyan_Xiao",
        "verified": true
      },
      {
        "created_at": "2023-08-06T17:00:07.000Z",
        "description": "ヨルシカ◂Ⓘ▸/ゲーム🎮/カルピス🥛/ユニクロ👒/小孩@acenanami/可爱姐姐@lum1neko/🏳️‍⚧️🍥",
        "entities": {
          "description": {
            "mentions": [
              {
                "end": 37,
                "start": 27,
                "username": "acenanami"
              },
              {
                "end": 51,
                "start": 42,
                "username": "lum1neko"
              }
            ]
          }
        },
        "id": "1688233455363219456",
        "name": "𝓒𝓻𝔂𝓼𝓽𝓪𝓵𝓵𝓲𝓷𝓮 𝓢𝓱𝓲𝓷𝓮",
        "pinned_tweet_id": "1837849254397977009",
        "profile_image_url": "https://pbs.twimg.com/profile_images/1842483893506887680/QuvrUH1r_normal.jpg",
        "protected": false,
        "public_metrics": {
          "followers_count": 710,
          "following_count": 888,
          "like_count": 121324,
          "listed_count": 4,
          "tweet_count": 22955
        },
        "username": "Susiethegamer",
        "verified": false
      }
    ]
  }
}