{
  "data": {
    "article": {},
    "attachments": {},
    "author_id": "1643490407094030338",
    "conversation_id": "2024511398882267523",
    "created_at": "2026-02-19T16:16:10.000Z",
    "edit_controls": {
      "editable_until": "2026-02-19T17:16:10.000Z",
      "edits_remaining": 5,
      "is_edit_eligible": false
    },
    "edit_history_tweet_ids": [
      "2024518383195328845"
    ],
    "entities": {
      "mentions": [
        {
          "end": 16,
          "id": "1169174984389885952",
          "start": 0,
          "username": "Angel_SaveUsAll"
        },
        {
          "end": 30,
          "id": "1964331185590718464",
          "start": 17,
          "username": "breakcoreWTF"
        }
      ]
    },
    "geo": {},
    "id": "2024518383195328845",
    "in_reply_to_user_id": "1169174984389885952",
    "lang": "zh",
    "note_tweet": {
      "entities": {}
    },
    "possibly_sensitive": false,
    "public_metrics": {
      "bookmark_count": 0,
      "impression_count": 0,
      "like_count": 0,
      "quote_count": 0,
      "reply_count": 0,
      "retweet_count": 0
    },
    "referenced_tweets": [
      {
        "id": "2024517221234381003",
        "type": "replied_to"
      }
    ],
    "reply_settings": "everyone",
    "text": "@Angel_SaveUsAll @breakcoreWTF 诡秘这有点诡异了"
  },
  "includes": {
    "tweets": [
      {
        "article": {},
        "attachments": {},
        "author_id": "1643490407094030338",
        "conversation_id": "2024511398882267523",
        "created_at": "2026-02-19T16:16:10.000Z",
        "edit_controls": {
          "editable_until": "2026-02-19T17:16:10.000Z",
          "edits_remaining": 5,
          "is_edit_eligible": false
        },
        "edit_history_tweet_ids": [
          "2024518383195328845"
        ],
        "entities": {
          "mentions": [
            {
              "end": 16,
              "id": "1169174984389885952",
              "start": 0,
              "username": "Angel_SaveUsAll"
            },
            {
              "end": 30,
              "id": "1964331185590718464",
              "start": 17,
              "username": "breakcoreWTF"
            }
          ]
        },
        "geo": {},
        "id": "2024518383195328845",
        "in_reply_to_user_id": "1169174984389885952",
        "lang": "zh",
        "note_tweet": {
          "entities": {}
        },
        "possibly_sensitive": false,
        "public_metrics": {
          "bookmark_count": 0,
          "impression_count": 0,
          "like_count": 0,
          "quote_count": 0,
          "reply_count": 0,
          "retweet_count": 0
        },
        "referenced_tweets": [
          {
            "id": "2024517221234381003",
            "type": "replied_to"
          }
        ],
        "reply_settings": "everyone",
        "text": "@Angel_SaveUsAll @breakcoreWTF 诡秘这有点诡异了"
      },
      {
        "article": {},
        "attachments": {},
        "author_id": "1169174984389885952",
        "conversation_id": "2024511398882267523",
        "created_at": "2026-02-19T16:11:33.000Z",
        "edit_controls": {
          "editable_until": "2026-02-19T17:11:33.000Z",
          "edits_remaining": 5,
          "is_edit_eligible": false
        },
        "edit_history_tweet_ids": [
          "2024517221234381003"
        ],
        "entities": {
          "mentions": [
            {
              "end": 13,
              "id": "1964331185590718464",
              "start": 0,
              "username": "breakcoreWTF"
            }
          ]
        },
        "geo": {},
        "id": "2024517221234381003",
        "in_reply_to_user_id": "1964331185590718464",
        "lang": "zh",
        "note_tweet": {
          "entities": {}
        },
        "possibly_sensitive": false,
        "public_metrics": {
          "bookmark_count": 0,
          "impression_count": 4,
          "like_count": 2,
          "quote_count": 0,
          "reply_count": 1,
          "retweet_count": 0
        },
        "referenced_tweets": [
          {
            "id": "2024511398882267523",
            "type": "replied_to"
          }
        ],
        "reply_settings": "everyone",
        "text": "@breakcoreWTF 姐妹你怎么一直看黄"
      }
    ],
    "users": [
      {
        "created_at": "2023-04-05T05:47:19.000Z",
        "description": "Paradoxのゲームで戦略を練る日々。特にヨーロッパの文化史探求が好きです。\n\n興味分野：数学、外国文学（INFP）📚\n\n好きなもの：東方、アズールレーン、松坂さんと塩ちゃん。\n\n 持病（双極性障害など）Gganbu:@bolckAshley\n\nℵ₀n-β1naria",
        "entities": {
          "description": {
            "mentions": [
              {
                "end": 122,
                "start": 110,
                "username": "bolckAshley"
              }
            ]
          }
        },
        "id": "1643490407094030338",
        "name": "イレンナ",
        "profile_image_url": "https://pbs.twimg.com/profile_images/2018810990268436480/IVOmWUUv_normal.jpg",
        "protected": false,
        "public_metrics": {
          "followers_count": 3550,
          "following_count": 1066,
          "like_count": 34310,
          "listed_count": 8,
          "media_count": 317,
          "tweet_count": 4217
        },
        "username": "Usam8964",
        "verified": false
      },
      {
        "created_at": "2019-09-04T09:07:06.000Z",
        "description": "救贖天使 含糖 新人画师，阴湿蕾蕾 只是会吃神秘小药片💊💊噶手手🩸🔪 情绪不稳定/BPD/焦虑症 舞萌 经常碎碎念EN&CN OK 日本語苦手 欢迎同类找我聊天贴贴🍥姐妹@linwei130 @yianmiao1026",
        "entities": {
          "description": {
            "mentions": [
              {
                "end": 95,
                "start": 85,
                "username": "linwei130"
              },
              {
                "end": 109,
                "start": 96,
                "username": "yianmiao1026"
              }
            ]
          }
        },
        "id": "1169174984389885952",
        "location": "New York, NY",
        "name": "靜滯立場重度依賴✟升天✟",
        "pinned_tweet_id": "2021599664840016205",
        "profile_image_url": "https://pbs.twimg.com/profile_images/1961716234724036608/pQ-MrTXe_normal.jpg",
        "protected": false,
        "public_metrics": {
          "followers_count": 887,
          "following_count": 292,
          "like_count": 5360,
          "listed_count": 3,
          "media_count": 182,
          "tweet_count": 2055
        },
        "username": "Angel_SaveUsAll",
        "verified": true
      },
      {
        "created_at": "2025-09-06T14:13:55.000Z",
        "description": "OD丨自伤丨Vocaloid丨音游丨友跨顺女丨少关心我\n不喜欢的直接b 推特是垃圾桶口无遮拦 同类回fo",
        "id": "1964331185590718464",
        "location": "🚪50/88 熟推免",
        "name": "箸",
        "pinned_tweet_id": "2024039744276189189",
        "profile_image_url": "https://pbs.twimg.com/profile_images/2019848796881186816/pdjXkx-3_normal.jpg",
        "protected": false,
        "public_metrics": {
          "followers_count": 573,
          "following_count": 571,
          "like_count": 8918,
          "listed_count": 0,
          "media_count": 150,
          "tweet_count": 2773
        },
        "username": "breakcoreWTF",
        "verified": false
      }
    ]
  }
}